hprc_spider/__init__.py
hprc_spider/__main__.py
hprc_spider/spider.py
hprc_spider-0.1.0.dist-info/METADATA
hprc_spider-0.1.0.dist-info/WHEEL
hprc_spider-0.1.0.dist-info/top_level.txt
hprc_spider-0.1.0.dist-info/RECORD
